Workbook
Name CommencementDate: Forecast!$D$10
Name GrowthRate: Forecast!$D$9

Sheet Forecast
B3: Forecast Financial Results
B5: ="12 Months Ending "&TEXT(EOMONTH(CommencementDate,12),"MMM-YY") -> 12 Months Ending Mar-27
B8: Assumptions | D8: Variable
B9: Annual Growth Rate | D9: 0.03
B10: Commencement Date | D10: =EOMONTH(TODAY(),-1)+1 -> 46082
B13: Revenue | D13: Ann. Gr. | F13: =CommencementDate -> 46082 | G13: =EOMONTH(F13,1) -> 46142 | H13: =EOMONTH(G13,1) -> 46173 | I13: =EOMONTH(H13,1) -> 46203 | J13: =EOMONTH(I13,1) -> 46234 | K13: =EOMONTH(J13,1) -> 46265 | L13: =EOMONTH(K13,1) -> 46295 | M13: =EOMONTH(L13,1) -> 46326 | N13: =EOMONTH(M13,1) -> 46356 | ... Q13: =EOMONTH(P13,1) -> 46446 | S13: Total
B15: Food | D15: 0.03 | F15: =INDEX(Historic!$D:$O,MATCH($B15,Historic!$B:$B,0),MATCH(EOMONTH(F$13,-12),Historic!$D$8:$O$8,0))*(1+IF($D15="",GrowthRate,$D15)) -> 10300 | G15: =INDEX(Historic!$D:$O,MATCH($B15,Historic!$B:$B,0),MATCH(EOMONTH(G$13,-12),Historic!$D$8:$O$8,0))*(1+IF($D15="",GrowthRate,$D15)) -> 10300 | H15: =INDEX(Historic!$D:$O,MATCH($B15,Historic!$B:$B,0),MATCH(EOMONTH(H$13,-12),Historic!$D$8:$O$8,0))*(1+IF($D15="",GrowthRate,$D15)) -> 10300 | I15: =INDEX(Historic!$D:$O,MATCH($B15,Historic!$B:$B,0),MATCH(EOMONTH(I$13,-12),Historic!$D$8:$O$8,0))*(1+IF($D15="",GrowthRate,$D15)) -> 10300 | J15: =INDEX(Historic!$D:$O,MATCH($B15,Historic!$B:$B,0),MATCH(EOMONTH(J$13,-12),Historic!$D$8:$O$8,0))*(1+IF($D15="",GrowthRate,$D15)) -> 10300 | K15: =INDEX(Historic!$D:$O,MATCH($B15,Historic!$B:$B,0),MATCH(EOMONTH(K$13,-12),Historic!$D$8:$O$8,0))*(1+IF($D15="",GrowthRate,$D15)) -> 10300 | L15: =INDEX(Historic!$D:$O,MATCH($B15,Historic!$B:$B,0),MATCH(EOMONTH(L$13,-12),Historic!$D$8:$O$8,0))*(1+IF($D15="",GrowthRate,$D15)) -> 10300 | M15: =INDEX(Historic!$D:$O,MATCH($B15,Historic!$B:$B,0),MATCH(EOMONTH(M$13,-12),Historic!$D$8:$O$8,0))*(1+IF($D15="",GrowthRate,$D15)) -> 10300 | ... Q15: =INDEX(Historic!$D:$O,MATCH($B15,Historic!$B:$B,0),MATCH(EOMONTH(Q$13,-12),Historic!$D$8:$O$8,0))*(1+IF($D15="",GrowthRate,$D15)) -> 10300 | S15: =SUM(F15:Q15) -> 123600
F16: =F15/F$21 -> 0.68132958 | G16: =G15/G$21 -> 0.68132958 | H16: =H15/H$21 -> 0.68132958 | I16: =I15/I$21 -> 0.68132958 | J16: =J15/J$21 -> 0.68132958 | K16: =K15/K$21 -> 0.68132958 | L16: =L15/L$21 -> 0.68132958 | M16: =M15/M$21 -> 0.68132958 | ... Q16: =Q15/Q$21 -> 0.68132958 | S16: =S15/S$21 -> 0.68132958
B17: Beverage | D17: 0.025 | F17: =INDEX(Historic!$D:$O,MATCH($B17,Historic!$B:$B,0),MATCH(EOMONTH(F$13,-12),Historic!$D$8:$O$8,0))*(1+IF($D17="",GrowthRate,$D17)) -> 3587.5 | G17: =INDEX(Historic!$D:$O,MATCH($B17,Historic!$B:$B,0),MATCH(EOMONTH(G$13,-12),Historic!$D$8:$O$8,0))*(1+IF($D17="",GrowthRate,$D17)) -> 3587.5 | H17: =INDEX(Historic!$D:$O,MATCH($B17,Historic!$B:$B,0),MATCH(EOMONTH(H$13,-12),Historic!$D$8:$O$8,0))*(1+IF($D17="",GrowthRate,$D17)) -> 3587.5 | I17: =INDEX(Historic!$D:$O,MATCH($B17,Historic!$B:$B,0),MATCH(EOMONTH(I$13,-12),Historic!$D$8:$O$8,0))*(1+IF($D17="",GrowthRate,$D17)) -> 3587.5 | J17: =INDEX(Historic!$D:$O,MATCH($B17,Historic!$B:$B,0),MATCH(EOMONTH(J$13,-12),Historic!$D$8:$O$8,0))*(1+IF($D17="",GrowthRate,$D17)) -> 3587.5 | K17: =INDEX(Historic!$D:$O,MATCH($B17,Historic!$B:$B,0),MATCH(EOMONTH(K$13,-12),Historic!$D$8:$O$8,0))*(1+IF($D17="",GrowthRate,$D17)) -> 3587.5 | L17: =INDEX(Historic!$D:$O,MATCH($B17,Historic!$B:$B,0),MATCH(EOMONTH(L$13,-12),Historic!$D$8:$O$8,0))*(1+IF($D17="",GrowthRate,$D17)) -> 3587.5 | M17: =INDEX(Historic!$D:$O,MATCH($B17,Historic!$B:$B,0),MATCH(EOMONTH(M$13,-12),Historic!$D$8:$O$8,0))*(1+IF($D17="",GrowthRate,$D17)) -> 3587.5 | ... Q17: =INDEX(Historic!$D:$O,MATCH($B17,Historic!$B:$B,0),MATCH(EOMONTH(Q$13,-12),Historic!$D$8:$O$8,0))*(1+IF($D17="",GrowthRate,$D17)) -> 3587.5 | S17: =SUM(F17:Q17) -> 43050
F18: =F17/F$21 -> 0.23730776 | G18: =G17/G$21 -> 0.23730776 | H18: =H17/H$21 -> 0.23730776 | I18: =I17/I$21 -> 0.23730776 | J18: =J17/J$21 -> 0.23730776 | K18: =K17/K$21 -> 0.23730776 | L18: =L17/L$21 -> 0.23730776 | M18: =M17/M$21 -> 0.23730776 | ... Q18: =Q17/Q$21 -> 0.23730776 | S18: =S17/S$21 -> 0.23730776
B19: Retail | D19: 0.025 | F19: =INDEX(Historic!$D:$O,MATCH($B19,Historic!$B:$B,0),MATCH(EOMONTH(F$13,-12),Historic!$D$8:$O$8,0))*(1+IF($D19="",GrowthRate,$D19)) -> 1230 | G19: =INDEX(Historic!$D:$O,MATCH($B19,Historic!$B:$B,0),MATCH(EOMONTH(G$13,-12),Historic!$D$8:$O$8,0))*(1+IF($D19="",GrowthRate,$D19)) -> 1230 | H19: =INDEX(Historic!$D:$O,MATCH($B19,Historic!$B:$B,0),MATCH(EOMONTH(H$13,-12),Historic!$D$8:$O$8,0))*(1+IF($D19="",GrowthRate,$D19)) -> 1230 | I19: =INDEX(Historic!$D:$O,MATCH($B19,Historic!$B:$B,0),MATCH(EOMONTH(I$13,-12),Historic!$D$8:$O$8,0))*(1+IF($D19="",GrowthRate,$D19)) -> 1230 | J19: =INDEX(Historic!$D:$O,MATCH($B19,Historic!$B:$B,0),MATCH(EOMONTH(J$13,-12),Historic!$D$8:$O$8,0))*(1+IF($D19="",GrowthRate,$D19)) -> 1230 | K19: =INDEX(Historic!$D:$O,MATCH($B19,Historic!$B:$B,0),MATCH(EOMONTH(K$13,-12),Historic!$D$8:$O$8,0))*(1+IF($D19="",GrowthRate,$D19)) -> 1230 | L19: =INDEX(Historic!$D:$O,MATCH($B19,Historic!$B:$B,0),MATCH(EOMONTH(L$13,-12),Historic!$D$8:$O$8,0))*(1+IF($D19="",GrowthRate,$D19)) -> 1230 | M19: =INDEX(Historic!$D:$O,MATCH($B19,Historic!$B:$B,0),MATCH(EOMONTH(M$13,-12),Historic!$D$8:$O$8,0))*(1+IF($D19="",GrowthRate,$D19)) -> 1230 | ... Q19: =INDEX(Historic!$D:$O,MATCH($B19,Historic!$B:$B,0),MATCH(EOMONTH(Q$13,-12),Historic!$D$8:$O$8,0))*(1+IF($D19="",GrowthRate,$D19)) -> 1230 | S19: =SUM(F19:Q19) -> 14760
F20: =F19/F$21 -> 0.081362659 | G20: =G19/G$21 -> 0.081362659 | H20: =H19/H$21 -> 0.081362659 | I20: =I19/I$21 -> 0.081362659 | J20: =J19/J$21 -> 0.081362659 | K20: =K19/K$21 -> 0.081362659 | L20: =L19/L$21 -> 0.081362659 | M20: =M19/M$21 -> 0.081362659 | ... Q20: =Q19/Q$21 -> 0.081362659 | S20: =S19/S$21 -> 0.081362659
B21: Total Revenue | D21: =S21/Historic!Q16-1 -> 0.028401361 | F21: =SUM(F15,F17,F19) -> 15117.5 | G21: =SUM(G15,G17,G19) -> 15117.5 | H21: =SUM(H15,H17,H19) -> 15117.5 | I21: =SUM(I15,I17,I19) -> 15117.5 | J21: =SUM(J15,J17,J19) -> 15117.5 | K21: =SUM(K15,K17,K19) -> 15117.5 | L21: =SUM(L15,L17,L19) -> 15117.5 | M21: =SUM(M15,M17,M19) -> 15117.5 | ... Q21: =SUM(Q15,Q17,Q19) -> 15117.5 | S21: =SUM(S15,S17,S19) -> 181410
B24: Cost of Sales | D24: Ann. Gr. | F24: =CommencementDate -> 46082 | G24: =EOMONTH(F24,1) -> 46142 | H24: =EOMONTH(G24,1) -> 46173 | I24: =EOMONTH(H24,1) -> 46203 | J24: =EOMONTH(I24,1) -> 46234 | K24: =EOMONTH(J24,1) -> 46265 | L24: =EOMONTH(K24,1) -> 46295 | M24: =EOMONTH(L24,1) -> 46326 | N24: =EOMONTH(M24,1) -> 46356 | ... Q24: =EOMONTH(P24,1) -> 46446 | S24: Total
B26: Food COS | D26: 0.05 | F26: =INDEX(Historic!$D:$O,MATCH($B26,Historic!$B:$B,0),MATCH(EOMONTH(F$13,-12),Historic!$D$8:$O$8,0))*(1+IF($D26="",GrowthRate,$D26)) -> 2625 | G26: =INDEX(Historic!$D:$O,MATCH($B26,Historic!$B:$B,0),MATCH(EOMONTH(G$13,-12),Historic!$D$8:$O$8,0))*(1+IF($D26="",GrowthRate,$D26)) -> 2625 | H26: =INDEX(Historic!$D:$O,MATCH($B26,Historic!$B:$B,0),MATCH(EOMONTH(H$13,-12),Historic!$D$8:$O$8,0))*(1+IF($D26="",GrowthRate,$D26)) -> 2625 | I26: =INDEX(Historic!$D:$O,MATCH($B26,Historic!$B:$B,0),MATCH(EOMONTH(I$13,-12),Historic!$D$8:$O$8,0))*(1+IF($D26="",GrowthRate,$D26)) -> 2625 | J26: =INDEX(Historic!$D:$O,MATCH($B26,Historic!$B:$B,0),MATCH(EOMONTH(J$13,-12),Historic!$D$8:$O$8,0))*(1+IF($D26="",GrowthRate,$D26)) -> 2625 | K26: =INDEX(Historic!$D:$O,MATCH($B26,Historic!$B:$B,0),MATCH(EOMONTH(K$13,-12),Historic!$D$8:$O$8,0))*(1+IF($D26="",GrowthRate,$D26)) -> 2625 | L26: =INDEX(Historic!$D:$O,MATCH($B26,Historic!$B:$B,0),MATCH(EOMONTH(L$13,-12),Historic!$D$8:$O$8,0))*(1+IF($D26="",GrowthRate,$D26)) -> 2625 | M26: =INDEX(Historic!$D:$O,MATCH($B26,Historic!$B:$B,0),MATCH(EOMONTH(M$13,-12),Historic!$D$8:$O$8,0))*(1+IF($D26="",GrowthRate,$D26)) -> 2625 | ... Q26: =INDEX(Historic!$D:$O,MATCH($B26,Historic!$B:$B,0),MATCH(EOMONTH(Q$13,-12),Historic!$D$8:$O$8,0))*(1+IF($D26="",GrowthRate,$D26)) -> 2625 | S26: =SUM(F26:Q26) -> 31500
F27: =F26/F15 -> 0.25485437 | G27: =G26/G15 -> 0.25485437 | H27: =H26/H15 -> 0.25485437 | I27: =I26/I15 -> 0.25485437 | J27: =J26/J15 -> 0.25485437 | K27: =K26/K15 -> 0.25485437 | L27: =L26/L15 -> 0.25485437 | M27: =M26/M15 -> 0.25485437 | ... Q27: =Q26/Q15 -> 0.25485437 | S27: =S26/S15 -> 0.25485437
B28: Beverage COS | F28: =INDEX(Historic!$D:$O,MATCH($B28,Historic!$B:$B,0),MATCH(EOMONTH(F$13,-12),Historic!$D$8:$O$8,0))*(1+IF($D28="",GrowthRate,$D28)) -> 793.1 | G28: =INDEX(Historic!$D:$O,MATCH($B28,Historic!$B:$B,0),MATCH(EOMONTH(G$13,-12),Historic!$D$8:$O$8,0))*(1+IF($D28="",GrowthRate,$D28)) -> 793.1 | H28: =INDEX(Historic!$D:$O,MATCH($B28,Historic!$B:$B,0),MATCH(EOMONTH(H$13,-12),Historic!$D$8:$O$8,0))*(1+IF($D28="",GrowthRate,$D28)) -> 793.1 | I28: =INDEX(Historic!$D:$O,MATCH($B28,Historic!$B:$B,0),MATCH(EOMONTH(I$13,-12),Historic!$D$8:$O$8,0))*(1+IF($D28="",GrowthRate,$D28)) -> 793.1 | J28: =INDEX(Historic!$D:$O,MATCH($B28,Historic!$B:$B,0),MATCH(EOMONTH(J$13,-12),Historic!$D$8:$O$8,0))*(1+IF($D28="",GrowthRate,$D28)) -> 793.1 | K28: =INDEX(Historic!$D:$O,MATCH($B28,Historic!$B:$B,0),MATCH(EOMONTH(K$13,-12),Historic!$D$8:$O$8,0))*(1+IF($D28="",GrowthRate,$D28)) -> 793.1 | L28: =INDEX(Historic!$D:$O,MATCH($B28,Historic!$B:$B,0),MATCH(EOMONTH(L$13,-12),Historic!$D$8:$O$8,0))*(1+IF($D28="",GrowthRate,$D28)) -> 793.1 | M28: =INDEX(Historic!$D:$O,MATCH($B28,Historic!$B:$B,0),MATCH(EOMONTH(M$13,-12),Historic!$D$8:$O$8,0))*(1+IF($D28="",GrowthRate,$D28)) -> 793.1 | ... Q28: =INDEX(Historic!$D:$O,MATCH($B28,Historic!$B:$B,0),MATCH(EOMONTH(Q$13,-12),Historic!$D$8:$O$8,0))*(1+IF($D28="",GrowthRate,$D28)) -> 793.1 | S28: =SUM(F28:Q28) -> 9517.2
F29: =F28/F17 -> 0.22107317 | G29: =G28/G17 -> 0.22107317 | H29: =H28/H17 -> 0.22107317 | I29: =I28/I17 -> 0.22107317 | J29: =J28/J17 -> 0.22107317 | K29: =K28/K17 -> 0.22107317 | L29: =L28/L17 -> 0.22107317 | M29: =M28/M17 -> 0.22107317 | ... Q29: =Q28/Q17 -> 0.22107317 | S29: =S28/S17 -> 0.22107317
B30: Retail COS | F30: =INDEX(Historic!$D:$O,MATCH($B30,Historic!$B:$B,0),MATCH(EOMONTH(F$13,-12),Historic!$D$8:$O$8,0))*(1+IF($D30="",GrowthRate,$D30)) -> 618 | G30: =INDEX(Historic!$D:$O,MATCH($B30,Historic!$B:$B,0),MATCH(EOMONTH(G$13,-12),Historic!$D$8:$O$8,0))*(1+IF($D30="",GrowthRate,$D30)) -> 618 | H30: =INDEX(Historic!$D:$O,MATCH($B30,Historic!$B:$B,0),MATCH(EOMONTH(H$13,-12),Historic!$D$8:$O$8,0))*(1+IF($D30="",GrowthRate,$D30)) -> 618 | I30: =INDEX(Historic!$D:$O,MATCH($B30,Historic!$B:$B,0),MATCH(EOMONTH(I$13,-12),Historic!$D$8:$O$8,0))*(1+IF($D30="",GrowthRate,$D30)) -> 618 | J30: =INDEX(Historic!$D:$O,MATCH($B30,Historic!$B:$B,0),MATCH(EOMONTH(J$13,-12),Historic!$D$8:$O$8,0))*(1+IF($D30="",GrowthRate,$D30)) -> 618 | K30: =INDEX(Historic!$D:$O,MATCH($B30,Historic!$B:$B,0),MATCH(EOMONTH(K$13,-12),Historic!$D$8:$O$8,0))*(1+IF($D30="",GrowthRate,$D30)) -> 618 | L30: =INDEX(Historic!$D:$O,MATCH($B30,Historic!$B:$B,0),MATCH(EOMONTH(L$13,-12),Historic!$D$8:$O$8,0))*(1+IF($D30="",GrowthRate,$D30)) -> 618 | M30: =INDEX(Historic!$D:$O,MATCH($B30,Historic!$B:$B,0),MATCH(EOMONTH(M$13,-12),Historic!$D$8:$O$8,0))*(1+IF($D30="",GrowthRate,$D30)) -> 618 | ... Q30: =INDEX(Historic!$D:$O,MATCH($B30,Historic!$B:$B,0),MATCH(EOMONTH(Q$13,-12),Historic!$D$8:$O$8,0))*(1+IF($D30="",GrowthRate,$D30)) -> 618 | S30: =SUM(F30:Q30) -> 7416
F31: =F30/F19 -> 0.50243902 | G31: =G30/G19 -> 0.50243902 | H31: =H30/H19 -> 0.50243902 | I31: =I30/I19 -> 0.50243902 | J31: =J30/J19 -> 0.50243902 | K31: =K30/K19 -> 0.50243902 | L31: =L30/L19 -> 0.50243902 | M31: =M30/M19 -> 0.50243902 | ... Q31: =Q30/Q19 -> 0.50243902 | S31: =S30/S19 -> 0.50243902
B32: Total Cost of Sales | D32: =S32/Historic!Q27-1 -> 0.042919897 | F32: =SUM(F26,F28,F30) -> 4036.1 | G32: =SUM(G26,G28,G30) -> 4036.1 | H32: =SUM(H26,H28,H30) -> 4036.1 | I32: =SUM(I26,I28,I30) -> 4036.1 | J32: =SUM(J26,J28,J30) -> 4036.1 | K32: =SUM(K26,K28,K30) -> 4036.1 | L32: =SUM(L26,L28,L30) -> 4036.1 | M32: =SUM(M26,M28,M30) -> 4036.1 | ... Q32: =SUM(Q26,Q28,Q30) -> 4036.1 | S32: =SUM(F32:Q32) -> 48433.2
F33: =F32/F21 -> 0.26698197 | G33: =G32/G21 -> 0.26698197 | H33: =H32/H21 -> 0.26698197 | I33: =I32/I21 -> 0.26698197 | J33: =J32/J21 -> 0.26698197 | K33: =K32/K21 -> 0.26698197 | L33: =L32/L21 -> 0.26698197 | M33: =M32/M21 -> 0.26698197 | ... Q33: =Q32/Q21 -> 0.26698197 | S33: =S32/S21 -> 0.26698197
B36: Gross Profit | D36: =S36/Historic!Q31-1 -> 0.023213296 | F36: =+F21-F32 -> 11081.4 | G36: =+G21-G32 -> 11081.4 | H36: =+H21-H32 -> 11081.4 | I36: =+I21-I32 -> 11081.4 | J36: =+J21-J32 -> 11081.4 | K36: =+K21-K32 -> 11081.4 | L36: =+L21-L32 -> 11081.4 | M36: =+M21-M32 -> 11081.4 | ... Q36: =+Q21-Q32 -> 11081.4 | S36: =SUM(F36:Q36) -> 132976.8
F37: =F36/F21 -> 0.73301803 | G37: =G36/G21 -> 0.73301803 | H37: =H36/H21 -> 0.73301803 | I37: =I36/I21 -> 0.73301803 | J37: =J36/J21 -> 0.73301803 | K37: =K36/K21 -> 0.73301803 | L37: =L36/L21 -> 0.73301803 | M37: =M36/M21 -> 0.73301803 | ... Q37: =Q36/Q21 -> 0.73301803 | S37: =S36/S21 -> 0.73301803
B40: Expenses | D40: Ann. Gr. | F40: =CommencementDate -> 46082 | G40: =EOMONTH(F40,1) -> 46142 | H40: =EOMONTH(G40,1) -> 46173 | I40: =EOMONTH(H40,1) -> 46203 | J40: =EOMONTH(I40,1) -> 46234 | K40: =EOMONTH(J40,1) -> 46265 | L40: =EOMONTH(K40,1) -> 46295 | M40: =EOMONTH(L40,1) -> 46326 | N40: =EOMONTH(M40,1) -> 46356 | ... Q40: =EOMONTH(P40,1) -> 46446 | S40: Total
B42: Wages & Salary | D42: 0.035 | F42: =INDEX(Historic!$D:$O,MATCH($B42,Historic!$B:$B,0),MATCH(EOMONTH(F$13,-12),Historic!$D$8:$O$8,0))*(1+IF($D42="",GrowthRate,$D42)) -> 5175 | G42: =INDEX(Historic!$D:$O,MATCH($B42,Historic!$B:$B,0),MATCH(EOMONTH(G$13,-12),Historic!$D$8:$O$8,0))*(1+IF($D42="",GrowthRate,$D42)) -> 5175 | H42: =INDEX(Historic!$D:$O,MATCH($B42,Historic!$B:$B,0),MATCH(EOMONTH(H$13,-12),Historic!$D$8:$O$8,0))*(1+IF($D42="",GrowthRate,$D42)) -> 5175 | I42: =INDEX(Historic!$D:$O,MATCH($B42,Historic!$B:$B,0),MATCH(EOMONTH(I$13,-12),Historic!$D$8:$O$8,0))*(1+IF($D42="",GrowthRate,$D42)) -> 5175 | J42: =INDEX(Historic!$D:$O,MATCH($B42,Historic!$B:$B,0),MATCH(EOMONTH(J$13,-12),Historic!$D$8:$O$8,0))*(1+IF($D42="",GrowthRate,$D42)) -> 5175 | K42: =INDEX(Historic!$D:$O,MATCH($B42,Historic!$B:$B,0),MATCH(EOMONTH(K$13,-12),Historic!$D$8:$O$8,0))*(1+IF($D42="",GrowthRate,$D42)) -> 5175 | L42: =INDEX(Historic!$D:$O,MATCH($B42,Historic!$B:$B,0),MATCH(EOMONTH(L$13,-12),Historic!$D$8:$O$8,0))*(1+IF($D42="",GrowthRate,$D42)) -> 5175 | M42: =INDEX(Historic!$D:$O,MATCH($B42,Historic!$B:$B,0),MATCH(EOMONTH(M$13,-12),Historic!$D$8:$O$8,0))*(1+IF($D42="",GrowthRate,$D42)) -> 5175 | ... Q42: =INDEX(Historic!$D:$O,MATCH($B42,Historic!$B:$B,0),MATCH(EOMONTH(Q$13,-12),Historic!$D$8:$O$8,0))*(1+IF($D42="",GrowthRate,$D42)) -> 5175 | S42: =SUM(F42:Q42) -> 62100
F43: =F42/F$21 -> 0.34231851 | G43: =G42/G$21 -> 0.34231851 | H43: =H42/H$21 -> 0.34231851 | I43: =I42/I$21 -> 0.34231851 | J43: =J42/J$21 -> 0.34231851 | K43: =K42/K$21 -> 0.34231851 | L43: =L42/L$21 -> 0.34231851 | M43: =M42/M$21 -> 0.34231851 | ... Q43: =Q42/Q$21 -> 0.34231851 | S43: =S42/S$21 -> 0.34231851
B44: Repairs & Maintenance | D44: 0.04 | F44: =INDEX(Historic!$D:$O,MATCH($B44,Historic!$B:$B,0),MATCH(EOMONTH(F$13,-12),Historic!$D$8:$O$8,0))*(1+IF($D44="",GrowthRate,$D44)) -> 520 | G44: =INDEX(Historic!$D:$O,MATCH($B44,Historic!$B:$B,0),MATCH(EOMONTH(G$13,-12),Historic!$D$8:$O$8,0))*(1+IF($D44="",GrowthRate,$D44)) -> 520 | H44: =INDEX(Historic!$D:$O,MATCH($B44,Historic!$B:$B,0),MATCH(EOMONTH(H$13,-12),Historic!$D$8:$O$8,0))*(1+IF($D44="",GrowthRate,$D44)) -> 520 | I44: =INDEX(Historic!$D:$O,MATCH($B44,Historic!$B:$B,0),MATCH(EOMONTH(I$13,-12),Historic!$D$8:$O$8,0))*(1+IF($D44="",GrowthRate,$D44)) -> 520 | J44: =INDEX(Historic!$D:$O,MATCH($B44,Historic!$B:$B,0),MATCH(EOMONTH(J$13,-12),Historic!$D$8:$O$8,0))*(1+IF($D44="",GrowthRate,$D44)) -> 520 | K44: =INDEX(Historic!$D:$O,MATCH($B44,Historic!$B:$B,0),MATCH(EOMONTH(K$13,-12),Historic!$D$8:$O$8,0))*(1+IF($D44="",GrowthRate,$D44)) -> 520 | L44: =INDEX(Historic!$D:$O,MATCH($B44,Historic!$B:$B,0),MATCH(EOMONTH(L$13,-12),Historic!$D$8:$O$8,0))*(1+IF($D44="",GrowthRate,$D44)) -> 520 | M44: =INDEX(Historic!$D:$O,MATCH($B44,Historic!$B:$B,0),MATCH(EOMONTH(M$13,-12),Historic!$D$8:$O$8,0))*(1+IF($D44="",GrowthRate,$D44)) -> 520 | ... Q44: =INDEX(Historic!$D:$O,MATCH($B44,Historic!$B:$B,0),MATCH(EOMONTH(Q$13,-12),Historic!$D$8:$O$8,0))*(1+IF($D44="",GrowthRate,$D44)) -> 520 | S44: =SUM(F44:Q44) -> 6240
F45: =F44/F$21 -> 0.034397222 | G45: =G44/G$21 -> 0.034397222 | H45: =H44/H$21 -> 0.034397222 | I45: =I44/I$21 -> 0.034397222 | J45: =J44/J$21 -> 0.034397222 | K45: =K44/K$21 -> 0.034397222 | L45: =L44/L$21 -> 0.034397222 | M45: =M44/M$21 -> 0.034397222 | ... Q45: =Q44/Q$21 -> 0.034397222 | S45: =S44/S$21 -> 0.034397222
B46: Computer & Software | D46: 0.025 | F46: =INDEX(Historic!$D:$O,MATCH($B46,Historic!$B:$B,0),MATCH(EOMONTH(F$13,-12),Historic!$D$8:$O$8,0))*(1+IF($D46="",GrowthRate,$D46)) -> 205 | G46: =INDEX(Historic!$D:$O,MATCH($B46,Historic!$B:$B,0),MATCH(EOMONTH(G$13,-12),Historic!$D$8:$O$8,0))*(1+IF($D46="",GrowthRate,$D46)) -> 205 | H46: =INDEX(Historic!$D:$O,MATCH($B46,Historic!$B:$B,0),MATCH(EOMONTH(H$13,-12),Historic!$D$8:$O$8,0))*(1+IF($D46="",GrowthRate,$D46)) -> 205 | I46: =INDEX(Historic!$D:$O,MATCH($B46,Historic!$B:$B,0),MATCH(EOMONTH(I$13,-12),Historic!$D$8:$O$8,0))*(1+IF($D46="",GrowthRate,$D46)) -> 205 | J46: =INDEX(Historic!$D:$O,MATCH($B46,Historic!$B:$B,0),MATCH(EOMONTH(J$13,-12),Historic!$D$8:$O$8,0))*(1+IF($D46="",GrowthRate,$D46)) -> 205 | K46: =INDEX(Historic!$D:$O,MATCH($B46,Historic!$B:$B,0),MATCH(EOMONTH(K$13,-12),Historic!$D$8:$O$8,0))*(1+IF($D46="",GrowthRate,$D46)) -> 205 | L46: =INDEX(Historic!$D:$O,MATCH($B46,Historic!$B:$B,0),MATCH(EOMONTH(L$13,-12),Historic!$D$8:$O$8,0))*(1+IF($D46="",GrowthRate,$D46)) -> 205 | M46: =INDEX(Historic!$D:$O,MATCH($B46,Historic!$B:$B,0),MATCH(EOMONTH(M$13,-12),Historic!$D$8:$O$8,0))*(1+IF($D46="",GrowthRate,$D46)) -> 205 | ... Q46: =INDEX(Historic!$D:$O,MATCH($B46,Historic!$B:$B,0),MATCH(EOMONTH(Q$13,-12),Historic!$D$8:$O$8,0))*(1+IF($D46="",GrowthRate,$D46)) -> 205 | S46: =SUM(F46:Q46) -> 2460
F47: =F46/F$21 -> 0.013560443 | G47: =G46/G$21 -> 0.013560443 | H47: =H46/H$21 -> 0.013560443 | I47: =I46/I$21 -> 0.013560443 | J47: =J46/J$21 -> 0.013560443 | K47: =K46/K$21 -> 0.013560443 | L47: =L46/L$21 -> 0.013560443 | M47: =M46/M$21 -> 0.013560443 | ... Q47: =Q46/Q$21 -> 0.013560443 | S47: =S46/S$21 -> 0.013560443
B48: Rates & Utilities | D48: 0.05 | F48: =INDEX(Historic!$D:$O,MATCH($B48,Historic!$B:$B,0),MATCH(EOMONTH(F$13,-12),Historic!$D$8:$O$8,0))*(1+IF($D48="",GrowthRate,$D48)) -> 367.5 | G48: =INDEX(Historic!$D:$O,MATCH($B48,Historic!$B:$B,0),MATCH(EOMONTH(G$13,-12),Historic!$D$8:$O$8,0))*(1+IF($D48="",GrowthRate,$D48)) -> 367.5 | H48: =INDEX(Historic!$D:$O,MATCH($B48,Historic!$B:$B,0),MATCH(EOMONTH(H$13,-12),Historic!$D$8:$O$8,0))*(1+IF($D48="",GrowthRate,$D48)) -> 367.5 | I48: =INDEX(Historic!$D:$O,MATCH($B48,Historic!$B:$B,0),MATCH(EOMONTH(I$13,-12),Historic!$D$8:$O$8,0))*(1+IF($D48="",GrowthRate,$D48)) -> 367.5 | J48: =INDEX(Historic!$D:$O,MATCH($B48,Historic!$B:$B,0),MATCH(EOMONTH(J$13,-12),Historic!$D$8:$O$8,0))*(1+IF($D48="",GrowthRate,$D48)) -> 367.5 | K48: =INDEX(Historic!$D:$O,MATCH($B48,Historic!$B:$B,0),MATCH(EOMONTH(K$13,-12),Historic!$D$8:$O$8,0))*(1+IF($D48="",GrowthRate,$D48)) -> 367.5 | L48: =INDEX(Historic!$D:$O,MATCH($B48,Historic!$B:$B,0),MATCH(EOMONTH(L$13,-12),Historic!$D$8:$O$8,0))*(1+IF($D48="",GrowthRate,$D48)) -> 367.5 | M48: =INDEX(Historic!$D:$O,MATCH($B48,Historic!$B:$B,0),MATCH(EOMONTH(M$13,-12),Historic!$D$8:$O$8,0))*(1+IF($D48="",GrowthRate,$D48)) -> 367.5 | ... Q48: =INDEX(Historic!$D:$O,MATCH($B48,Historic!$B:$B,0),MATCH(EOMONTH(Q$13,-12),Historic!$D$8:$O$8,0))*(1+IF($D48="",GrowthRate,$D48)) -> 367.5 | S48: =SUM(F48:Q48) -> 4410
F49: =F48/F$21 -> 0.024309575 | G49: =G48/G$21 -> 0.024309575 | H49: =H48/H$21 -> 0.024309575 | I49: =I48/I$21 -> 0.024309575 | J49: =J48/J$21 -> 0.024309575 | K49: =K48/K$21 -> 0.024309575 | L49: =L48/L$21 -> 0.024309575 | M49: =M48/M$21 -> 0.024309575 | ... Q49: =Q48/Q$21 -> 0.024309575 | S49: =S48/S$21 -> 0.024309575
B50: Operating Equipment | D50: 0.03 | F50: =INDEX(Historic!$D:$O,MATCH($B50,Historic!$B:$B,0),MATCH(EOMONTH(F$13,-12),Historic!$D$8:$O$8,0))*(1+IF($D50="",GrowthRate,$D50)) -> 1030 | G50: =INDEX(Historic!$D:$O,MATCH($B50,Historic!$B:$B,0),MATCH(EOMONTH(G$13,-12),Historic!$D$8:$O$8,0))*(1+IF($D50="",GrowthRate,$D50)) -> 1030 | H50: =INDEX(Historic!$D:$O,MATCH($B50,Historic!$B:$B,0),MATCH(EOMONTH(H$13,-12),Historic!$D$8:$O$8,0))*(1+IF($D50="",GrowthRate,$D50)) -> 1030 | I50: =INDEX(Historic!$D:$O,MATCH($B50,Historic!$B:$B,0),MATCH(EOMONTH(I$13,-12),Historic!$D$8:$O$8,0))*(1+IF($D50="",GrowthRate,$D50)) -> 1030 | J50: =INDEX(Historic!$D:$O,MATCH($B50,Historic!$B:$B,0),MATCH(EOMONTH(J$13,-12),Historic!$D$8:$O$8,0))*(1+IF($D50="",GrowthRate,$D50)) -> 1030 | K50: =INDEX(Historic!$D:$O,MATCH($B50,Historic!$B:$B,0),MATCH(EOMONTH(K$13,-12),Historic!$D$8:$O$8,0))*(1+IF($D50="",GrowthRate,$D50)) -> 1030 | L50: =INDEX(Historic!$D:$O,MATCH($B50,Historic!$B:$B,0),MATCH(EOMONTH(L$13,-12),Historic!$D$8:$O$8,0))*(1+IF($D50="",GrowthRate,$D50)) -> 1030 | M50: =INDEX(Historic!$D:$O,MATCH($B50,Historic!$B:$B,0),MATCH(EOMONTH(M$13,-12),Historic!$D$8:$O$8,0))*(1+IF($D50="",GrowthRate,$D50)) -> 1030 | ... Q50: =INDEX(Historic!$D:$O,MATCH($B50,Historic!$B:$B,0),MATCH(EOMONTH(Q$13,-12),Historic!$D$8:$O$8,0))*(1+IF($D50="",GrowthRate,$D50)) -> 1030 | S50: =SUM(F50:Q50) -> 12360
F51: =F50/F$21 -> 0.068132958 | G51: =G50/G$21 -> 0.068132958 | H51: =H50/H$21 -> 0.068132958 | I51: =I50/I$21 -> 0.068132958 | J51: =J50/J$21 -> 0.068132958 | K51: =K50/K$21 -> 0.068132958 | L51: =L50/L$21 -> 0.068132958 | M51: =M50/M$21 -> 0.068132958 | ... Q51: =Q50/Q$21 -> 0.068132958 | S51: =S50/S$21 -> 0.068132958
B52: Total Expenses | D52: =S52/Historic!Q47-1 -> 0.035106383 | F52: =SUM(F42,F44,F46,F48,F50) -> 7297.5 | G52: =SUM(G42,G44,G46,G48,G50) -> 7297.5 | H52: =SUM(H42,H44,H46,H48,H50) -> 7297.5 | I52: =SUM(I42,I44,I46,I48,I50) -> 7297.5 | J52: =SUM(J42,J44,J46,J48,J50) -> 7297.5 | K52: =SUM(K42,K44,K46,K48,K50) -> 7297.5 | L52: =SUM(L42,L44,L46,L48,L50) -> 7297.5 | M52: =SUM(M42,M44,M46,M48,M50) -> 7297.5 | ... Q52: =SUM(Q42,Q44,Q46,Q48,Q50) -> 7297.5 | S52: =SUM(F52:Q52) -> 87570
F53: =F52/F$21 -> 0.4827187 | G53: =G52/G$21 -> 0.4827187 | H53: =H52/H$21 -> 0.4827187 | I53: =I52/I$21 -> 0.4827187 | J53: =J52/J$21 -> 0.4827187 | K53: =K52/K$21 -> 0.4827187 | L53: =L52/L$21 -> 0.4827187 | M53: =M52/M$21 -> 0.4827187 | ... Q53: =Q52/Q$21 -> 0.4827187 | S53: =S52/S$21 -> 0.4827187
B56: Net Profit | D56: =S56/Historic!Q51-1 -> 0.001031746 | F56: =+F36-F52 -> 3783.9 | G56: =+G36-G52 -> 3783.9 | H56: =+H36-H52 -> 3783.9 | I56: =+I36-I52 -> 3783.9 | J56: =+J36-J52 -> 3783.9 | K56: =+K36-K52 -> 3783.9 | L56: =+L36-L52 -> 3783.9 | M56: =+M36-M52 -> 3783.9 | ... Q56: =+Q36-Q52 -> 3783.9 | S56: =SUM(F56:Q56) -> 45406.8
F57: =F56/F21 -> 0.25029932 | G57: =G56/G21 -> 0.25029932 | H57: =H56/H21 -> 0.25029932 | I57: =I56/I21 -> 0.25029932 | J57: =J56/J21 -> 0.25029932 | K57: =K56/K21 -> 0.25029932 | L57: =L56/L21 -> 0.25029932 | M57: =M56/M21 -> 0.25029932 | ... Q57: =Q56/Q21 -> 0.25029932 | S57: =S56/S21 -> 0.25029932

Sheet Historic
B3: Actual Historic Financial Results
B5: ="12 Months Ending "&TEXT(EOMONTH(CommencementDate,-1),"MMM-YY") -> 12 Months Ending Feb-26
B8: Revenue | D8: =EOMONTH(CommencementDate,-12) -> 45747 | E8: =EOMONTH(D8,1) -> 45777 | F8: =EOMONTH(E8,1) -> 45808 | G8: =EOMONTH(F8,1) -> 45838 | H8: =EOMONTH(G8,1) -> 45869 | I8: =EOMONTH(H8,1) -> 45900 | J8: =EOMONTH(I8,1) -> 45930 | K8: =EOMONTH(J8,1) -> 45961 | L8: =EOMONTH(K8,1) -> 45991 | ... O8: =EOMONTH(N8,1) -> 46081 | Q8: Total
B10: Food | D10: 10000 | E10: 10000 | F10: 10000 | G10: 10000 | H10: 10000 | I10: 10000 | J10: 10000 | K10: 10000 | L10: 10000 | M10: 10000 | N10: 10000 | O10: 10000 | Q10: =SUM(D10:O10) -> 120000
D11: =D10/D$16 -> 0.68027211 | E11: =E10/E$16 -> 0.68027211 | F11: =F10/F$16 -> 0.68027211 | G11: =G10/G$16 -> 0.68027211 | H11: =H10/H$16 -> 0.68027211 | I11: =I10/I$16 -> 0.68027211 | J11: =J10/J$16 -> 0.68027211 | K11: =K10/K$16 -> 0.68027211 | ... O11: =O10/O$16 -> 0.68027211 | Q11: =Q10/Q$16 -> 0.68027211
B12: Beverage | D12: 3500 | E12: 3500 | F12: 3500 | G12: 3500 | H12: 3500 | I12: 3500 | J12: 3500 | K12: 3500 | L12: 3500 | M12: 3500 | N12: 3500 | O12: 3500 | Q12: =SUM(D12:O12) -> 42000
D13: =D12/D$16 -> 0.23809524 | E13: =E12/E$16 -> 0.23809524 | F13: =F12/F$16 -> 0.23809524 | G13: =G12/G$16 -> 0.23809524 | H13: =H12/H$16 -> 0.23809524 | I13: =I12/I$16 -> 0.23809524 | J13: =J12/J$16 -> 0.23809524 | K13: =K12/K$16 -> 0.23809524 | ... O13: =O12/O$16 -> 0.23809524 | Q13: =Q12/Q$16 -> 0.23809524
B14: Retail | D14: 1200 | E14: 1200 | F14: 1200 | G14: 1200 | H14: 1200 | I14: 1200 | J14: 1200 | K14: 1200 | L14: 1200 | M14: 1200 | N14: 1200 | O14: 1200 | Q14: =SUM(D14:O14) -> 14400
D15: =D14/D$16 -> 0.081632653 | E15: =E14/E$16 -> 0.081632653 | F15: =F14/F$16 -> 0.081632653 | G15: =G14/G$16 -> 0.081632653 | H15: =H14/H$16 -> 0.081632653 | I15: =I14/I$16 -> 0.081632653 | J15: =J14/J$16 -> 0.081632653 | K15: =K14/K$16 -> 0.081632653 | ... O15: =O14/O$16 -> 0.081632653 | Q15: =Q14/Q$16 -> 0.081632653
B16: Total Revenue | D16: =SUM(D10,D12,D14) -> 14700 | E16: =SUM(E10,E12,E14) -> 14700 | F16: =SUM(F10,F12,F14) -> 14700 | G16: =SUM(G10,G12,G14) -> 14700 | H16: =SUM(H10,H12,H14) -> 14700 | I16: =SUM(I10,I12,I14) -> 14700 | J16: =SUM(J10,J12,J14) -> 14700 | K16: =SUM(K10,K12,K14) -> 14700 | ... O16: =SUM(O10,O12,O14) -> 14700 | Q16: =SUM(Q10,Q12,Q14) -> 176400
B19: Cost of Sales | D19: =CommencementDate -> 46082 | E19: =EOMONTH(D19,1) -> 46142 | F19: =EOMONTH(E19,1) -> 46173 | G19: =EOMONTH(F19,1) -> 46203 | H19: =EOMONTH(G19,1) -> 46234 | I19: =EOMONTH(H19,1) -> 46265 | J19: =EOMONTH(I19,1) -> 46295 | K19: =EOMONTH(J19,1) -> 46326 | L19: =EOMONTH(K19,1) -> 46356 | ... O19: =EOMONTH(N19,1) -> 46446 | Q19: Total
B21: Food COS | D21: 2500 | E21: 2500 | F21: 2500 | G21: 2500 | H21: 2500 | I21: 2500 | J21: 2500 | K21: 2500 | L21: 2500 | M21: 2500 | N21: 2500 | O21: 2500 | Q21: =SUM(D21:O21) -> 30000
D22: =D21/D10 -> 0.25 | E22: =E21/E10 -> 0.25 | F22: =F21/F10 -> 0.25 | G22: =G21/G10 -> 0.25 | H22: =H21/H10 -> 0.25 | I22: =I21/I10 -> 0.25 | J22: =J21/J10 -> 0.25 | K22: =K21/K10 -> 0.25 | ... O22: =O21/O10 -> 0.25 | Q22: =Q21/Q10 -> 0.25
B23: Beverage COS | D23: 770 | E23: 770 | F23: 770 | G23: 770 | H23: 770 | I23: 770 | J23: 770 | K23: 770 | L23: 770 | M23: 770 | N23: 770 | O23: 770 | Q23: =SUM(D23:O23) -> 9240
D24: =D23/D12 -> 0.22 | E24: =E23/E12 -> 0.22 | F24: =F23/F12 -> 0.22 | G24: =G23/G12 -> 0.22 | H24: =H23/H12 -> 0.22 | I24: =I23/I12 -> 0.22 | J24: =J23/J12 -> 0.22 | K24: =K23/K12 -> 0.22 | ... O24: =O23/O12 -> 0.22 | Q24: =Q23/Q12 -> 0.22
B25: Retail COS | D25: 600 | E25: 600 | F25: 600 | G25: 600 | H25: 600 | I25: 600 | J25: 600 | K25: 600 | L25: 600 | M25: 600 | N25: 600 | O25: 600 | Q25: =SUM(D25:O25) -> 7200
D26: =D25/D14 -> 0.5 | E26: =E25/E14 -> 0.5 | F26: =F25/F14 -> 0.5 | G26: =G25/G14 -> 0.5 | H26: =H25/H14 -> 0.5 | I26: =I25/I14 -> 0.5 | J26: =J25/J14 -> 0.5 | K26: =K25/K14 -> 0.5 | ... O26: =O25/O14 -> 0.5 | Q26: =Q25/Q14 -> 0.5
B27: Total Cost of Sales | D27: =SUM(D21,D23,D25) -> 3870 | E27: =SUM(E21,E23,E25) -> 3870 | F27: =SUM(F21,F23,F25) -> 3870 | G27: =SUM(G21,G23,G25) -> 3870 | H27: =SUM(H21,H23,H25) -> 3870 | I27: =SUM(I21,I23,I25) -> 3870 | J27: =SUM(J21,J23,J25) -> 3870 | K27: =SUM(K21,K23,K25) -> 3870 | ... O27: =SUM(O21,O23,O25) -> 3870 | Q27: =SUM(D27:O27) -> 46440
D28: =D27/D16 -> 0.26326531 | E28: =E27/E16 -> 0.26326531 | F28: =F27/F16 -> 0.26326531 | G28: =G27/G16 -> 0.26326531 | H28: =H27/H16 -> 0.26326531 | I28: =I27/I16 -> 0.26326531 | J28: =J27/J16 -> 0.26326531 | K28: =K27/K16 -> 0.26326531 | ... O28: =O27/O16 -> 0.26326531 | Q28: =Q27/Q16 -> 0.26326531
B31: Gross Profit | D31: =+D16-D27 -> 10830 | E31: =+E16-E27 -> 10830 | F31: =+F16-F27 -> 10830 | G31: =+G16-G27 -> 10830 | H31: =+H16-H27 -> 10830 | I31: =+I16-I27 -> 10830 | J31: =+J16-J27 -> 10830 | K31: =+K16-K27 -> 10830 | ... O31: =+O16-O27 -> 10830 | Q31: =SUM(D31:O31) -> 129960
D32: =D31/D16 -> 0.73673469 | E32: =E31/E16 -> 0.73673469 | F32: =F31/F16 -> 0.73673469 | G32: =G31/G16 -> 0.73673469 | H32: =H31/H16 -> 0.73673469 | I32: =I31/I16 -> 0.73673469 | J32: =J31/J16 -> 0.73673469 | K32: =K31/K16 -> 0.73673469 | ... O32: =O31/O16 -> 0.73673469 | Q32: =Q31/Q16 -> 0.73673469
B35: Expenses | D35: =CommencementDate -> 46082 | E35: =EOMONTH(D35,1) -> 46142 | F35: =EOMONTH(E35,1) -> 46173 | G35: =EOMONTH(F35,1) -> 46203 | H35: =EOMONTH(G35,1) -> 46234 | I35: =EOMONTH(H35,1) -> 46265 | J35: =EOMONTH(I35,1) -> 46295 | K35: =EOMONTH(J35,1) -> 46326 | L35: =EOMONTH(K35,1) -> 46356 | ... O35: =EOMONTH(N35,1) -> 46446 | Q35: Total
B37: Wages & Salary | D37: 5000 | E37: 5000 | F37: 5000 | G37: 5000 | H37: 5000 | I37: 5000 | J37: 5000 | K37: 5000 | L37: 5000 | M37: 5000 | N37: 5000 | O37: 5000 | Q37: =SUM(D37:O37) -> 60000
D38: =D37/D$16 -> 0.34013605 | E38: =E37/E$16 -> 0.34013605 | F38: =F37/F$16 -> 0.34013605 | G38: =G37/G$16 -> 0.34013605 | H38: =H37/H$16 -> 0.34013605 | I38: =I37/I$16 -> 0.34013605 | J38: =J37/J$16 -> 0.34013605 | K38: =K37/K$16 -> 0.34013605 | ... O38: =O37/O$16 -> 0.34013605 | Q38: =Q37/Q$16 -> 0.34013605
B39: Repairs & Maintenance | D39: 500 | E39: 500 | F39: 500 | G39: 500 | H39: 500 | I39: 500 | J39: 500 | K39: 500 | L39: 500 | M39: 500 | N39: 500 | O39: 500 | Q39: =SUM(D39:O39) -> 6000
D40: =D39/D$16 -> 0.034013605 | E40: =E39/E$16 -> 0.034013605 | F40: =F39/F$16 -> 0.034013605 | G40: =G39/G$16 -> 0.034013605 | H40: =H39/H$16 -> 0.034013605 | I40: =I39/I$16 -> 0.034013605 | J40: =J39/J$16 -> 0.034013605 | K40: =K39/K$16 -> 0.034013605 | ... O40: =O39/O$16 -> 0.034013605 | Q40: =Q39/Q$16 -> 0.034013605
B41: Computer & Software | D41: 200 | E41: 200 | F41: 200 | G41: 200 | H41: 200 | I41: 200 | J41: 200 | K41: 200 | L41: 200 | M41: 200 | N41: 200 | O41: 200 | Q41: =SUM(D41:O41) -> 2400
D42: =D41/D$16 -> 0.013605442 | E42: =E41/E$16 -> 0.013605442 | F42: =F41/F$16 -> 0.013605442 | G42: =G41/G$16 -> 0.013605442 | H42: =H41/H$16 -> 0.013605442 | I42: =I41/I$16 -> 0.013605442 | J42: =J41/J$16 -> 0.013605442 | K42: =K41/K$16 -> 0.013605442 | ... O42: =O41/O$16 -> 0.013605442 | Q42: =Q41/Q$16 -> 0.013605442
B43: Rates & Utilities | D43: 350 | E43: 350 | F43: 350 | G43: 350 | H43: 350 | I43: 350 | J43: 350 | K43: 350 | L43: 350 | M43: 350 | N43: 350 | O43: 350 | Q43: =SUM(D43:O43) -> 4200
D44: =D43/D$16 -> 0.023809524 | E44: =E43/E$16 -> 0.023809524 | F44: =F43/F$16 -> 0.023809524 | G44: =G43/G$16 -> 0.023809524 | H44: =H43/H$16 -> 0.023809524 | I44: =I43/I$16 -> 0.023809524 | J44: =J43/J$16 -> 0.023809524 | K44: =K43/K$16 -> 0.023809524 | ... O44: =O43/O$16 -> 0.023809524 | Q44: =Q43/Q$16 -> 0.023809524
B45: Operating Equipment | D45: 1000 | E45: 1000 | F45: 1000 | G45: 1000 | H45: 1000 | I45: 1000 | J45: 1000 | K45: 1000 | L45: 1000 | M45: 1000 | N45: 1000 | O45: 1000 | Q45: =SUM(D45:O45) -> 12000
D46: =D45/D$16 -> 0.068027211 | E46: =E45/E$16 -> 0.068027211 | F46: =F45/F$16 -> 0.068027211 | G46: =G45/G$16 -> 0.068027211 | H46: =H45/H$16 -> 0.068027211 | I46: =I45/I$16 -> 0.068027211 | J46: =J45/J$16 -> 0.068027211 | K46: =K45/K$16 -> 0.068027211 | ... O46: =O45/O$16 -> 0.068027211 | Q46: =Q45/Q$16 -> 0.068027211
B47: Total Expenses | D47: =SUM(D37,D39,D41,D43,D45) -> 7050 | E47: =SUM(E37,E39,E41,E43,E45) -> 7050 | F47: =SUM(F37,F39,F41,F43,F45) -> 7050 | G47: =SUM(G37,G39,G41,G43,G45) -> 7050 | H47: =SUM(H37,H39,H41,H43,H45) -> 7050 | I47: =SUM(I37,I39,I41,I43,I45) -> 7050 | J47: =SUM(J37,J39,J41,J43,J45) -> 7050 | K47: =SUM(K37,K39,K41,K43,K45) -> 7050 | ... O47: =SUM(O37,O39,O41,O43,O45) -> 7050 | Q47: =SUM(D47:O47) -> 84600
D48: =D47/D$16 -> 0.47959184 | E48: =E47/E$16 -> 0.47959184 | F48: =F47/F$16 -> 0.47959184 | G48: =G47/G$16 -> 0.47959184 | H48: =H47/H$16 -> 0.47959184 | I48: =I47/I$16 -> 0.47959184 | J48: =J47/J$16 -> 0.47959184 | K48: =K47/K$16 -> 0.47959184 | ... O48: =O47/O$16 -> 0.47959184 | Q48: =Q47/Q$16 -> 0.47959184
B51: Net Profit | D51: =+D31-D47 -> 3780 | E51: =+E31-E47 -> 3780 | F51: =+F31-F47 -> 3780 | G51: =+G31-G47 -> 3780 | H51: =+H31-H47 -> 3780 | I51: =+I31-I47 -> 3780 | J51: =+J31-J47 -> 3780 | K51: =+K31-K47 -> 3780 | ... O51: =+O31-O47 -> 3780 | Q51: =SUM(D51:O51) -> 45360
D52: =D51/D16 -> 0.25714286 | E52: =E51/E16 -> 0.25714286 | F52: =F51/F16 -> 0.25714286 | G52: =G51/G16 -> 0.25714286 | H52: =H51/H16 -> 0.25714286 | I52: =I51/I16 -> 0.25714286 | J52: =J51/J16 -> 0.25714286 | K52: =K51/K16 -> 0.25714286 | ... O52: =O51/O16 -> 0.25714286 | Q52: =Q51/Q16 -> 0.25714286
